{"widget_positions":{"wp_inactive_widgets":[],"cwp-primary-sidebar":["search-2","recent-posts-2","recent-comments-2","archives-2","categories-2","meta-2"],"cwp-secondary-sidebar":[],"footer-sidebar-1":["text-3"],"footer-sidebar-2":["media_gallery-3"],"footer-sidebar-3":["nav_menu-3"],"footer-sidebar-4":["custom_html-3"],"footer-sidebar-5":[],"footer-sidebar-6":[],"footer-sidebar-7":[],"footer-sidebar-8":[],"array_version":3},"widget_options":{"search":{"2":{"title":""},"_multiwidget":1},"recent-posts":{"2":{"title":"","number":5},"_multiwidget":1},"recent-comments":{"2":{"title":"","number":5},"_multiwidget":1},"archives":{"2":{"title":"","count":0,"dropdown":0},"_multiwidget":1},"categories":{"2":{"title":"","count":0,"hierarchical":0,"dropdown":0},"_multiwidget":1},"meta":{"2":{"title":""},"_multiwidget":1},"text":{"1":[],"_multiwidget":1,"3":{"title":"CosmosWP Travel","text":"Lorem ipsum dolor sit amet, consectetur adipisicing elit, sed do eiusmod tempor incididunt ut labore et dolore magna aliqua. Ut enim ad minim veniam,quis nostrud exercitation ullamco laboris nisi ut aliquip ex ea commodo\r\n\r\n<a href=\"https:\/\/www.demo.cosmoswp.com\/demo-10\/about\/\">Read More <i class=\"fas fa-angle-right\"><\/i><\/a>","filter":true,"visual":true}},"media_gallery":{"_multiwidget":1,"3":{"title":"Gallery","ids":[98,99,101,102,103,107],"columns":3,"size":"thumbnail","link_type":"post","orderby_random":false}},"nav_menu":{"_multiwidget":1,"3":{"title":"Usefull Links","nav_menu":3}},"custom_html":{"_multiwidget":1,"3":{"title":"Contact Info","content":"<b>LOCATION<\/b>\r\n<p>\r\n12356 Glassford Street Glasgow G1 1ULNew York, USA\r\n<\/p>\r\n<br>\r\n<b>EMAIL US<\/b> <br>\r\n<a href=\"mailto:noreply@cosmoswp.com\">\r\nnoreply@cosmoswp.com<\/a>\r\n<br>\r\n<br>\r\n<b>PHONE<\/b> <br>\r\n<p>\r\n\tT: +844 123 456 7\r\n<\/p>"}}}}